[
  {
    "id": 1,
    "question": "What is the capital city of Germany?",
    "options": [
      "Paris",
      "Berlin",
      "Madrid",
      " Moscow"
    ],
    "correctAnswers": [
      "Berlin"
    ]
  },
  {
    "id": 2,
    "question": "Which programming language is primarily used for web development?",
    "options": [
      "Python",
      "JavaScript",
      "C++",
      " html"
    ],
    "correctAnswers": [
      "JavaScript",
      "html"
    ]
  },
  {
    "id": 3,
    "question": "What does HTML stand for?",
    "options": [
      "HyperText Markup Language",
      "HighText Machine Language",
      "Hyper Transfer Markup Language"
    ],
    "correctAnswers": [
      "HyperText Markup Language"
    ]
  },
  {
    "id": 4,
    "question": "Which planet is known as the Red Planet?",
    "options": [
      "Earth",
      "Mars",
      "Venus"
    ],
    "correctAnswers": [
      "Mars"
    ]
  },
  {
    "id": 5,
    "question": "Who developed the theory of relativity?",
    "options": [
      "Isaac Newton",
      "Albert Einstein",
      "Galileo Galilei"
    ],
    "correctAnswers": [
      "Albert Einstein"
    ]
  },
  {
    "id": 6,
    "question": "Which of the following are JavaScript frameworks?",
    "options": [
      "React",
      "Django",
      "Vue"
    ],
    "correctAnswers": [
      "React",
      "Vue"
    ]
  },
  {
    "id": 7,
    "question": "In which year did World War II end?",
    "options": [
      "1945",
      "1939",
      "1918"
    ],
    "correctAnswers": [
      "1945"
    ]
  },
  {
    "id": 8,
    "question": "Which data structure uses FIFO (First In, First Out)?",
    "options": [
      "Stack",
      "Queue",
      "Tree"
    ],
    "correctAnswers": [
      "Queue"
    ]
  },
  {
    "id": 9,
    "question": "Which tag is used to include JavaScript in HTML?",
    "options": [
      "<js>",
      "<script>",
      "<javascript>"
    ],
    "correctAnswers": [
      "<script>"
    ]
  },
  {
    "id": 10,
    "question": "Which of the following are cloud service providers?",
    "options": [
      "AWS",
      "Azure",
      "Google Cloud"
    ],
    "correctAnswers": [
      "AWS",
      "Azure",
      "Google Cloud"
    ]
  },
  {
    "id": 11,
    "question": "How many in Dozens?",
    "options": [
      "10",
      "15",
      "12",
      "6"
    ],
    "correctAnswers": [
      "12"
    ]
  },
  {
    "id": 12,
    "question": "How many seasons?",
    "options": [
      "4",
      "5",
      "6",
      "7"
    ],
    "correctAnswers": [
      "7"
    ]
  },
  {
    "id": 13,
    "question": "How many world's total population is ? (in billion)",
    "options": [
      "7",
      "8",
      "9",
      "6"
    ],
    "correctAnswers": [
      "8"
    ]
  },
  {
    "id": 15,
    "question": "Who was the last Mughal King?",
    "options": [
      "Bahadur Shah Zafar",
      "Babur",
      "Taimur Lang",
      "Aurangzeb"
    ],
    "correctAnswers": [
      "Bahadur Shah Zafar"
    ]
  },
  {
    "id": 16,
    "question": "New Russian Capital?",
    "options": [
      "Grozhny",
      "Moscow"
    ],
    "correctAnswers": [
      "Moscow"
    ]
  },
  {
    "id": 17,
    "question": "odd Number(s)?",
    "options": [
      "1",
      "2",
      "3"
    ],
    "correctAnswers": [
      "1",
      "3"
    ]
  },
  {
    "id": 18,
    "question": "How many continents in the World (according to the latest discovery  by 2025)?",
    "options": [
      "6",
      "7",
      "8",
      "9"
    ],
    "correctAnswers": [
      "8"
    ]
  },
  {
    "id": 19,
    "question": "How many total month in a year?",
    "options": [
      "12",
      "10",
      "14",
      "15"
    ],
    "correctAnswers": [
      "12"
    ]
  },
  {
    "id": 20,
    "question": "Richest person in the world? ",
    "options": [
      "Elon Musk",
      "Jeff Bezos",
      "Bill Gates"
    ],
    "correctAnswers": [
      "Elon Musk"
    ]
  },
  {
    "id": 21,
    "question": "How many continents in the World (according to the latest discovery  by 2025)?",
    "options": [
      "6",
      "7",
      "8",
      "9"
    ],
    "correctAnswers": [
      "8"
    ]
  }
]